myCalculatorPackageN/__init__.py
myCalculatorPackageN/division/__init__.py
myCalculatorPackageN/division/divide.py
myCalculatorPackageN/multiplication/__init__.py
myCalculatorPackageN/multiplication/multiply.py
myCalculatorPackageN-0.0.2.dist-info/LICENSE.txt
myCalculatorPackageN-0.0.2.dist-info/METADATA
myCalculatorPackageN-0.0.2.dist-info/WHEEL
myCalculatorPackageN-0.0.2.dist-info/top_level.txt
myCalculatorPackageN-0.0.2.dist-info/RECORD
